README.md
setup.py
zeebe_worker/__init__.py
zeebe_worker/main.py
zeebe_worker.egg-info/PKG-INFO
zeebe_worker.egg-info/SOURCES.txt
zeebe_worker.egg-info/dependency_links.txt
zeebe_worker.egg-info/requires.txt
zeebe_worker.egg-info/top_level.txt