Metadata-Version: 1.2
Name: zeebe-worker
Version: 0.1.0
Summary: An easy worker wrapper to create Zeebe Workers
Home-page: https://gitlab.com/satys/libraries/zeebe-worker-py
Author: Satys
Author-email: info@satys.nl
License: MIT
Platform: UNKNOWN
Requires-Python: >= 3.5
